{"cameraMode":{"drawMode":0,"name":"Shaded","section":"Shading Mode"},"sceneLighting":false,"audioPlay":false,"sceneViewState":{"showFog":true,"showMaterialUpdate":false,"showSkybox":false,"showFlares":true,"showImageEffects":true,"showParticleSystems":true},"in2DMode":false,"pivot":{"x":0.013676377013325692,"y":0.20767004787921906,"z":-0.0028075315058231355},"rotation":{"x":0.217672660946846,"y":-0.2668488323688507,"z":0.06200578436255455,"w":0.9367913603782654},"size":0.03268716484308243,"orthographic":false}